matcher_py-0.5.8.dist-info/METADATA
matcher_py-0.5.8.dist-info/WHEEL
matcher_py/__init__.py
matcher_py/extension_types.py
matcher_py/matcher_py.cpython-39-x86_64-linux-gnu.so
matcher_py/matcher_py.pyi
matcher_py/py.typed
matcher_py-0.5.8.dist-info/RECORD
