Metadata-Version: 2.4
Name: matcher_py
Version: 0.5.8
Classifier: Development Status :: 5 - Production/Stable
Classifier: Intended Audience :: Developers
Classifier: License :: OSI Approved :: Apache Software License
Classifier: License :: OSI Approved :: MIT License
Classifier: Operating System :: MacOS
Classifier: Operating System :: Microsoft :: Windows
Classifier: Operating System :: POSIX :: Linux
Classifier: Programming Language :: Python :: 3
Classifier: Programming Language :: Python :: 3.8
Classifier: Programming Language :: Python :: 3.9
Classifier: Programming Language :: Python :: 3.10
Classifier: Programming Language :: Python :: 3.11
Classifier: Programming Language :: Python :: 3.12
Classifier: Programming Language :: Python :: 3.13
Classifier: Programming Language :: Python
Classifier: Programming Language :: Rust
Classifier: Typing :: Typed
Summary: A high-performance matcher designed to solve LOGICAL and TEXT VARIATIONS problems in word matching, implemented in Rust.
Home-Page: https://github.com/Lips7/Matcher
Author-email: Foster Guo <f975793771@gmail.com>
Requires-Python: >=3.8
Project-URL: homepage, https://github.com/Lips7/Matcher
Project-URL: repository, https://github.com/Lips7/Matcher
Project-URL: changelog, https://github.com/Lips7/Matcher/blob/master/CHANGELOG.md
